mbf_genomics/__init__.py
mbf_genomics/annotator.py
mbf_genomics/delayeddataframe.py
mbf_genomics/util.py
mbf_genomics/genes/__init__.py
mbf_genomics/genes/anno_tag_counts.py
mbf_genomics/genes/annotators.py
mbf_genomics/genes/genes.py
mbf_genomics/genes/genes_from.py
mbf_genomics/regions/__init__.py
mbf_genomics/regions/annotators.py
mbf_genomics/regions/convert.py
mbf_genomics/regions/plots.py
mbf_genomics/regions/regions.py
mbf_genomics/regions/regions_from.py
mbf_genomics/testing/__init__.py
mbf_genomics/testing/fixtures.py
mbf_genomics-0.4.dist-info/AUTHORS.rst
mbf_genomics-0.4.dist-info/LICENSE.txt
mbf_genomics-0.4.dist-info/METADATA
mbf_genomics-0.4.dist-info/WHEEL
mbf_genomics-0.4.dist-info/top_level.txt
mbf_genomics-0.4.dist-info/RECORD
